retail_sales_prediction/__init__.py
retail_sales_prediction/cli.py
retail_sales_prediction/main.py
retail_sales_prediction/version.py
retail_sales_prediction-0.1.0.dist-info/AUTHORS.rst
retail_sales_prediction-0.1.0.dist-info/LICENSE
retail_sales_prediction-0.1.0.dist-info/METADATA
retail_sales_prediction-0.1.0.dist-info/WHEEL
retail_sales_prediction-0.1.0.dist-info/entry_points.txt
retail_sales_prediction-0.1.0.dist-info/top_level.txt
retail_sales_prediction-0.1.0.dist-info/RECORD
