Metadata-Version: 2.1
Name: retail-sales-prediction
Version: 0.1.0
Summary: Python project to predict the sales of retail stores with machine learning
Home-page: https://github.com/amjadraza/retail_sales_prediction
Author: MA RAZA
Author-email: amjadraza24@gmail.com
License: MIT license
Keywords: retail_sales_prediction
Platform: UNKNOWN
Classifier: Development Status :: 2 - Pre-Alpha
Classifier: Intended Audience :: Developers
Classifier: License :: OSI Approved :: MIT License
Classifier: Natural Language :: English
Classifier: Programming Language :: Python :: 2
Classifier: Programming Language :: Python :: 2.7
Classifier: Programming Language :: Python :: 3
Classifier: Programming Language :: Python :: 3.4
Classifier: Programming Language :: Python :: 3.5
Classifier: Programming Language :: Python :: 3.6
Classifier: Programming Language :: Python :: 3.7
Requires-Dist: Click (>=6.0)
